{"lands":{"autotiles":[{"k":[16,12,0,0,0],"v":{"id":5,"t":[0,0],"tid":471}},{"k":[17,12,0,1,0],"v":{"id":5,"t":[0,0],"tid":324}},{"k":[18,12,0,0,0],"v":{"id":5,"t":[0,0],"tid":471}},{"k":[16,12,0,1,0],"v":{"id":5,"t":[0,0],"tid":324}},{"k":[17,12,0,0,0],"v":{"id":5,"t":[0,0],"tid":471}},{"k":[18,12,0,2,0],"v":{"id":5,"t":[0,0],"tid":584}},{"k":[19,12,0,1,0],"v":{"id":5,"t":[0,0],"tid":370}},{"k":[18,12,0,1,0],"v":{"id":5,"t":[0,0],"tid":308}},{"k":[19,12,0,0,0],"v":{"id":5,"t":[0,0],"tid":423}},{"k":[18,12,0,4,0],"v":{"id":5,"t":[0,0],"tid":584}},{"k":[19,12,0,3,0],"v":{"id":5,"t":[0,0],"tid":370}},{"k":[18,12,0,3,0],"v":{"id":5,"t":[0,0],"tid":584}},{"k":[19,12,0,2,0],"v":{"id":5,"t":[0,0],"tid":370}},{"k":[18,12,0,6,0],"v":{"id":5,"t":[0,0],"tid":584}},{"k":[19,12,0,5,0],"v":{"id":5,"t":[0,0],"tid":370}},{"k":[18,12,0,5,0],"v":{"id":5,"t":[0,0],"tid":584}},{"k":[19,12,0,4,0],"v":{"id":5,"t":[0,0],"tid":370}},{"k":[18,12,0,8,0],"v":{"id":5,"t":[0,0],"tid":584}},{"k":[19,12,0,7,0],"v":{"id":5,"t":[0,0],"tid":370}},{"k":[18,12,0,7,0],"v":{"id":5,"t":[0,0],"tid":584}},{"k":[19,12,0,6,0],"v":{"id":5,"t":[0,0],"tid":370}},{"k":[16,12,0,12,0],"v":{"id":5,"t":[0,0],"tid":318}},{"k":[17,12,0,11,0],"v":{"id":5,"t":[0,0],"tid":471}},{"k":[18,12,0,10,0],"v":{"id":5,"t":[0,0],"tid":584}},{"k":[19,12,0,9,0],"v":{"id":5,"t":[0,0],"tid":370}},{"k":[16,12,0,11,0],"v":{"id":5,"t":[0,0],"tid":471}},{"k":[18,12,0,9,0],"v":{"id":5,"t":[0,0],"tid":584}},{"k":[19,12,0,8,0],"v":{"id":5,"t":[0,0],"tid":370}},{"k":[17,12,0,13,0],"v":{"id":5,"t":[0,0],"tid":324}},{"k":[18,12,0,12,0],"v":{"id":5,"t":[0,0],"tid":318}},{"k":[19,12,0,11,0],"v":{"id":5,"t":[0,0],"tid":370}},{"k":[16,12,0,13,0],"v":{"id":5,"t":[0,0],"tid":324}},{"k":[17,12,0,12,0],"v":{"id":5,"t":[0,0],"tid":318}},{"k":[18,12,0,11,0],"v":{"id":5,"t":[0,0],"tid":62}},{"k":[19,12,0,10,0],"v":{"id":5,"t":[0,0],"tid":370}},{"k":[19,12,0,13,0],"v":{"id":5,"t":[0,0],"tid":372}},{"k":[18,12,0,13,0],"v":{"id":5,"t":[0,0],"tid":324}},{"k":[19,12,0,12,0],"v":{"id":5,"t":[0,0],"tid":370}},{"k":[17,0,0,1,0],"v":{"id":2,"t":[0,0],"tid":225}},{"k":[18,0,0,2,0],"v":{"id":2,"t":[0,0],"tid":318}},{"k":[17,0,0,3,0],"v":{"id":2,"t":[0,0],"tid":584}},{"k":[19,0,0,1,0],"v":{"id":2,"t":[0,0],"tid":423}},{"k":[17,0,0,2,0],"v":{"id":2,"t":[0,0],"tid":584}},{"k":[18,0,0,1,0],"v":{"id":2,"t":[0,0],"tid":471}},{"k":[18,0,0,4,0],"v":{"id":2,"t":[0,0],"tid":318}},{"k":[19,0,0,3,0],"v":{"id":2,"t":[0,0],"tid":370}},{"k":[17,0,0,5,0],"v":{"id":2,"t":[0,0],"tid":584}},{"k":[18,0,0,3,0],"v":{"id":2,"t":[0,0],"tid":318}},{"k":[19,0,0,2,0],"v":{"id":2,"t":[0,0],"tid":370}},{"k":[17,0,0,4,0],"v":{"id":2,"t":[0,0],"tid":584}},{"k":[18,0,0,6,0],"v":{"id":2,"t":[0,0],"tid":324}},{"k":[19,0,0,5,0],"v":{"id":2,"t":[0,0],"tid":370}},{"k":[18,0,0,5,0],"v":{"id":2,"t":[0,0],"tid":318}},{"k":[19,0,0,4,0],"v":{"id":2,"t":[0,0],"tid":370}},{"k":[17,0,0,6,0],"v":{"id":2,"t":[0,0],"tid":570}},{"k":[19,0,0,6,0],"v":{"id":2,"t":[0,0],"tid":372}}],"floors":[{"k":[16,0,0,6,0],"v":{"t":[3,0]}},{"k":[16,0,0,5,0],"v":{"t":[3,0]}},{"k":[16,0,0,8,0],"v":{"t":[0,1]}},{"k":[17,0,0,7,0],"v":{"t":[3,0]}},{"k":[16,0,0,7,0],"v":{"t":[3,0]}},{"k":[16,0,0,10,0],"v":{"t":[0,1]}},{"k":[17,0,0,9,0],"v":{"t":[0,1]}},{"k":[18,0,0,8,0],"v":{"t":[0,1]}},{"k":[16,1,0,9,0],"v":{"t":[0,0]}},{"k":[17,1,0,8,0],"v":{"t":[1,1]}},{"k":[16,2,0,8,0],"v":{"t":[3,0]}},{"k":[19,0,0,7,0],"v":{"t":[3,0]}},{"k":[16,0,0,9,0],"v":{"t":[0,1]}},{"k":[17,0,0,8,0],"v":{"t":[0,1]}},{"k":[16,1,0,8,0],"v":{"t":[0,0]}},{"k":[18,0,0,7,0],"v":{"t":[3,0]}},{"k":[16,0,0,12,0],"v":{"t":[0,1]}},{"k":[17,0,0,11,0],"v":{"t":[0,1]}},{"k":[18,0,0,10,0],"v":{"t":[0,1]}},{"k":[19,0,0,9,0],"v":{"t":[0,1]}},{"k":[16,1,0,11,0],"v":{"t":[0,0]}},{"k":[17,1,0,10,0],"v":{"t":[1,1]}},{"k":[18,1,0,9,0],"v":{"t":[1,1]}},{"k":[19,1,0,8,0],"v":{"t":[1,1]}},{"k":[16,2,0,10,0],"v":{"t":[3,0]}},{"k":[18,2,0,8,0],"v":{"t":[3,0]}},{"k":[16,0,0,11,0],"v":{"t":[0,1]}},{"k":[17,0,0,10,0],"v":{"t":[0,1]}},{"k":[18,0,0,9,0],"v":{"t":[0,1]}},{"k":[19,0,0,8,0],"v":{"t":[0,1]}},{"k":[16,1,0,10,0],"v":{"t":[0,0]}},{"k":[17,1,0,9,0],"v":{"t":[0,1]}},{"k":[18,1,0,8,0],"v":{"t":[0,1]}},{"k":[16,2,0,9,0],"v":{"t":[3,0]}},{"k":[17,2,0,8,0],"v":{"t":[3,0]}},{"k":[16,0,0,14,0],"v":{"t":[0,1]}},{"k":[17,0,0,13,0],"v":{"t":[0,1]}},{"k":[18,0,0,12,0],"v":{"t":[0,1]}},{"k":[19,0,0,11,0],"v":{"t":[0,1]}},{"k":[17,1,0,12,0],"v":{"t":[1,1]}},{"k":[18,1,0,11,0],"v":{"t":[1,1]}},{"k":[19,1,0,10,0],"v":{"t":[1,1]}},{"k":[19,2,0,9,0],"v":{"t":[3,0]}},{"k":[16,1,0,13,0],"v":{"t":[0,0]}},{"k":[16,12,0,2,0],"v":{"t":[0,1]}},{"k":[16,0,0,13,0],"v":{"t":[0,1]}},{"k":[17,0,0,12,0],"v":{"t":[0,1]}},{"k":[18,0,0,11,0],"v":{"t":[0,1]}},{"k":[19,0,0,10,0],"v":{"t":[0,1]}},{"k":[17,1,0,11,0],"v":{"t":[0,1]}},{"k":[19,1,0,9,0],"v":{"t":[0,1]}},{"k":[18,1,0,10,0],"v":{"t":[0,1]}},{"k":[16,2,0,11,0],"v":{"t":[3,0]}},{"k":[19,2,0,8,0],"v":{"t":[3,0]}},{"k":[16,1,0,12,0],"v":{"t":[0,0]}},{"k":[18,0,0,14,0],"v":{"t":[0,1]}},{"k":[19,0,0,13,0],"v":{"t":[0,1]}},{"k":[18,1,0,13,0],"v":{"t":[1,1]}},{"k":[17,1,0,14,0],"v":{"t":[1,1]}},{"k":[19,1,0,12,0],"v":{"t":[1,1]}},{"k":[16,2,0,14,0],"v":{"t":[3,0]}},{"k":[19,2,0,11,0],"v":{"t":[3,0]}},{"k":[16,12,0,4,0],"v":{"t":[0,1]}},{"k":[17,12,0,3,0],"v":{"t":[0,1]}},{"k":[17,0,0,14,0],"v":{"t":[0,1]}},{"k":[18,0,0,13,0],"v":{"t":[0,1]}},{"k":[19,0,0,12,0],"v":{"t":[0,1]}},{"k":[16,1,0,14,0],"v":{"t":[0,0]}},{"k":[17,1,0,13,0],"v":{"t":[0,1]}},{"k":[19,1,0,11,0],"v":{"t":[0,1]}},{"k":[18,1,0,12,0],"v":{"t":[0,1]}},{"k":[19,2,0,10,0],"v":{"t":[3,0]}},{"k":[16,12,0,3,0],"v":{"t":[0,1]}},{"k":[17,12,0,2,0],"v":{"t":[0,1]}},{"k":[19,1,0,14,0],"v":{"t":[1,1]}},{"k":[18,2,0,14,0],"v":{"t":[3,0]}},{"k":[19,2,0,13,0],"v":{"t":[3,0]}},{"k":[17,12,0,5,0],"v":{"t":[0,1]}},{"k":[16,12,0,6,0],"v":{"t":[0,1]}},{"k":[19,0,0,14,0],"v":{"t":[0,1]}},{"k":[19,1,0,13,0],"v":{"t":[0,1]}},{"k":[18,1,0,14,0],"v":{"t":[0,1]}},{"k":[17,2,0,14,0],"v":{"t":[3,0]}},{"k":[19,2,0,12,0],"v":{"t":[3,0]}},{"k":[17,12,0,4,0],"v":{"t":[0,1]}},{"k":[16,12,0,5,0],"v":{"t":[0,1]}},{"k":[17,12,0,7,0],"v":{"t":[0,1]}},{"k":[16,12,0,8,0],"v":{"t":[0,1]}},{"k":[19,2,0,14,0],"v":{"t":[3,0]}},{"k":[17,12,0,6,0],"v":{"t":[0,1]}},{"k":[16,12,0,7,0],"v":{"t":[0,1]}},{"k":[17,12,0,9,0],"v":{"t":[0,1]}},{"k":[16,12,0,10,0],"v":{"t":[0,1]}},{"k":[17,12,0,8,0],"v":{"t":[0,1]}},{"k":[16,12,0,9,0],"v":{"t":[0,1]}},{"k":[17,12,0,10,0],"v":{"t":[0,1]}},{"k":[16,12,0,14,0],"v":{"t":[3,0]}},{"k":[18,12,0,14,0],"v":{"t":[3,0]}},{"k":[17,13,0,14,0],"v":{"t":[3,0]}},{"k":[17,12,0,14,0],"v":{"t":[3,0]}},{"k":[16,13,0,14,0],"v":{"t":[3,0]}},{"k":[19,13,0,14,0],"v":{"t":[3,0]}},{"k":[19,12,0,14,0],"v":{"t":[3,0]}},{"k":[18,13,0,14,0],"v":{"t":[3,0]}},{"k":[16,0,0,0,0],"v":{"t":[3,0]}},{"k":[18,0,0,0,0],"v":{"t":[3,0]}},{"k":[16,0,0,2,0],"v":{"t":[3,0]}},{"k":[17,0,0,0,0],"v":{"t":[3,0]}},{"k":[16,0,0,1,0],"v":{"t":[3,0]}},{"k":[16,0,0,4,0],"v":{"t":[3,0]}},{"k":[16,0,0,3,0],"v":{"t":[3,0]}},{"k":[19,0,0,0,0],"v":{"t":[3,0]}}]},"moun":{"a":[{"k":[19,0,0,9,0],"v":{"b":true,"l":true,"sid":6,"t":true}},{"k":[18,0,0,10,0],"v":{"b":true,"l":true,"r":true,"sid":6,"t":true}},{"k":[17,0,0,11,0],"v":{"b":true,"l":true,"r":true,"sid":6,"t":true}},{"k":[16,0,0,12,0],"v":{"b":true,"l":true,"r":true,"sid":6,"t":true}},{"k":[16,1,0,11,0],"v":{"sid":6,"t":true}},{"k":[19,1,0,8,0],"v":{"b":true,"l":true,"sid":6}},{"k":[19,0,0,8,0],"v":{"b":true,"l":true,"sid":6}},{"k":[17,0,0,10,0],"v":{"b":true,"r":true,"sid":6,"t":true}},{"k":[18,0,0,9,0],"v":{"b":true,"l":true,"r":true,"sid":6,"t":true}},{"k":[16,0,0,11,0],"v":{"b":true,"l":true,"r":true,"sid":6}},{"k":[16,1,0,10,0],"v":{"b":true,"sid":6,"t":true}},{"k":[18,1,0,8,0],"v":{"l":true,"r":true,"sid":6}},{"k":[19,0,0,11,0],"v":{"b":true,"l":true,"sid":6,"t":true}},{"k":[18,0,0,12,0],"v":{"b":true,"l":true,"r":true,"sid":6,"t":true}},{"k":[17,0,0,13,0],"v":{"b":true,"l":true,"r":true,"sid":6,"t":true}},{"k":[16,0,0,14,0],"v":{"l":true,"r":true,"sid":6,"t":true}},{"k":[19,1,0,10,0],"v":{"b":true,"sid":6,"t":true}},{"k":[19,0,0,10,0],"v":{"b":true,"l":true,"sid":6,"t":true}},{"k":[18,0,0,11,0],"v":{"b":true,"l":true,"r":true,"sid":6,"t":true}},{"k":[17,0,0,12,0],"v":{"b":true,"l":true,"r":true,"sid":6,"t":true}},{"k":[16,0,0,13,0],"v":{"b":true,"l":true,"r":true,"sid":6,"t":true}},{"k":[19,1,0,9,0],"v":{"b":true,"sid":6,"t":true}},{"k":[18,0,0,14,0],"v":{"l":true,"r":true,"sid":6,"t":true}},{"k":[19,0,0,13,0],"v":{"b":true,"l":true,"sid":6,"t":true}},{"k":[17,1,0,14,0],"v":{"l":true,"r":true,"sid":6}},{"k":[19,1,0,12,0],"v":{"b":true,"sid":6,"t":true}},{"k":[19,0,0,12,0],"v":{"b":true,"l":true,"sid":6,"t":true}},{"k":[18,0,0,13,0],"v":{"b":true,"l":true,"r":true,"sid":6,"t":true}},{"k":[17,0,0,14,0],"v":{"l":true,"r":true,"sid":6,"t":true}},{"k":[16,1,0,14,0],"v":{"l":true,"r":true,"sid":6}},{"k":[19,1,0,11,0],"v":{"b":true,"sid":6,"t":true}},{"k":[19,1,0,14,0],"v":{"l":true,"sid":6,"t":true}},{"k":[19,0,0,14,0],"v":{"l":true,"sid":6,"t":true}},{"k":[18,1,0,14,0],"v":{"l":true,"r":true,"sid":6}},{"k":[19,1,0,13,0],"v":{"b":true,"sid":6,"t":true}},{"k":[16,12,0,14,0],"v":{"l":true,"r":true,"sid":6}},{"k":[18,12,0,14,0],"v":{"l":true,"r":true,"sid":6}},{"k":[17,12,0,14,0],"v":{"l":true,"r":true,"sid":6}},{"k":[19,12,0,14,0],"v":{"l":true,"sid":6}},{"k":[16,0,0,8,0],"v":{"b":true,"r":true,"sid":6}},{"k":[18,0,0,8,0],"v":{"b":true,"l":true,"r":true,"sid":6}},{"k":[17,0,0,9,0],"v":{"b":true,"l":true,"r":true,"sid":6,"t":true}},{"k":[16,0,0,10,0],"v":{"l":true,"sid":6,"wp":125}},{"k":[16,1,0,9,0],"v":{"b":true,"sid":6,"t":true}},{"k":[17,1,0,8,0],"v":{"l":true,"r":true,"sid":6}},{"k":[17,0,0,8,0],"v":{"b":true,"l":true,"r":true,"sid":6}},{"k":[16,0,0,9,0],"v":{"r":true,"sid":6,"t":true}},{"k":[16,1,0,8,0],"v":{"b":true,"r":true,"sid":6}}],"o":[]},"objs":{"list":[{"k":[18,1,0,11,0],"v":{"events":[{"id":1,"name":"Hero action","p":[],"r":{"1":{"bh":true,"c":[{"command":[8,"",-1,0,0,1,"4TH: ASSEMBLY"],"kind":1},{"command":[0,3,0,4,3,100,0,12,0,0,12,0],"kind":28}]},"2":{"bh":true,"c":[{"command":[8,"",-1,0,0,1,"4TH: ASSEMBLY"],"kind":1}]}},"sys":false}],"hId":-1,"id":1,"name":"OBJ0001","ooepf":false,"states":[{"cam":true,"climb":false,"dir":false,"f":2,"gid":4,"gk":10,"id":1,"move":false,"name":"State 1","pix":true,"pos":false,"stop":false,"sx":{"k":12,"v":1},"sy":{"k":12,"v":1},"sz":{"k":12,"v":1},"through":false,"x":0,"y":0},{"cam":true,"climb":false,"dir":false,"f":2,"gid":5,"gk":10,"id":2,"move":true,"name":"State 2","pix":true,"pos":false,"stop":false,"sx":{"k":12,"v":1},"sy":{"k":12,"v":1},"sz":{"k":12,"v":1},"through":false,"x":0,"y":0}]}},{"k":[17,0,0,0,0],"v":{"events":[{"id":1,"name":"Hero action","p":[],"r":{"1":{"bh":true,"c":[{"command":[8,"",-1,0,0,1,"[c]______ MEANS TO TAKE UP RESIDENCE AND BECOME ESTABLISHED[/c]"],"kind":1},{"command":[8,"",-1,0,0,1,"[c]EX: DO [/c]"],"kind":1},{"command":[3,0,3,3,"-",1,"RUSH","-",1,"BECOME","-",1,"SETTLE"],"kind":31},{"children":[{"command":[8,"",-1,0,0,1,"[c]RUSH[/c]"],"kind":1},{"command":[7,0,0,3,19,0,0,0,0,0,0],"kind":20},{"command":[0,3,0,11,3,100,0,12,0,0,12,0],"kind":28}],"command":[1],"kind":32},{"children":[{"command":[8,"",-1,0,0,1,"[c]BECOME[/c]"],"kind":1},{"command":[7,0,0,3,19,0,0,0,0,0,0],"kind":20},{"command":[0,3,0,11,3,100,0,12,0,0,12,0],"kind":28}],"command":[2],"kind":32},{"children":[{"command":[8,"",-1,0,0,1,"[c]SETTLE[/c]"],"kind":1},{"command":[7,0,0,3,16,0,0,0,0,0,0],"kind":20},{"command":[0,3,0,8,3,100,0,12,0,0,12,0],"kind":28}],"command":[3],"kind":32},{"command":[],"kind":33}]}},"sys":false}],"hId":-1,"id":7,"name":"OBJ0007","ooepf":false,"states":[{"cam":true,"climb":false,"dir":false,"gid":114,"gk":10,"id":1,"move":true,"name":"State 1","pix":true,"pos":false,"stop":false,"sx":{"k":12,"v":1},"sy":{"k":12,"v":1},"sz":{"k":12,"v":1},"through":false,"x":0,"y":0}]}}]},"objs3d":{"a":[{"k":[17,12,0,12,0],"v":{"did":116}},{"k":[18,1,0,13,0,50,50,180],"v":{"did":104}},{"k":[17,1,0,9,0],"v":{"did":106}},{"k":[18,12,0,1,0],"v":{"did":116}},{"k":[18,1,0,10,0,50,50,90],"v":{"did":105}}],"o":[]},"sprites":{"list":[{"k":[16,0,0,7,0],"v":{"f":false,"k":4,"t":[4,7,1,3]}},{"k":[17,12,0,9,0],"v":{"k":4,"t":[4,7,1,1]}}],"overflow":[],"walls":[]}}